MANIFEST.in
setup.py
robotnik/__init__.py
robotnik/app.py
robotnik/config.py
robotnik/local.conf
robotnik/server.py
robotnik/util.py
robotnik/handlers/__init__.py
robotnik/handlers/base.py
robotnik/handlers/egg.py
robotnik/static/css/base.css
robotnik/static/css/reset.css
robotnik/templates/base.html
robotnik/templates/index.html
robotnik/templates/result.html
robotnik/test/__init__.py
robotnik/test/test_string_version_comparison.py