Metadata-Version: 1.0
Name: robotnik
Version: 0.2
Summary: Robotnik, python gemnasium
Home-page: http://github.com/guilhermef/robotnik
Author: Guilherme Souza
Author-email: guivideojob@gmail.com
License: MIT
Keywords: gemnasium robotnik
Platform: UNKNOWN
Classifier: Development Status :: 3 - Alpha
Classifier: Intended Audience :: Developers
Classifier: License :: OSI Approved :: MIT License
Classifier: Natural Language :: English
Classifier: Operating System :: MacOS
Classifier: Operating System :: POSIX :: Linux
Classifier: Programming Language :: Python :: 2.6
Classifier: Programming Language :: Python :: 2.7
